enigma_lipe_caio/__init__.py
enigma_lipe_caio/funcoes_adicionais.py
enigma_lipe_caio/funcoes_criadas.py
enigma_lipe_caio-0.2.dist-info/METADATA
enigma_lipe_caio-0.2.dist-info/WHEEL
enigma_lipe_caio-0.2.dist-info/top_level.txt
enigma_lipe_caio-0.2.dist-info/RECORD
