Metadata-Version: 2.1
Name: enigma-lipe-caio
Version: 0.2
Author: Lipe Barretto
Author-email: lfjanot87@gmail.com
Classifier: Programming Language :: Python :: 3
Classifier: License :: OSI Approved :: MIT License
Classifier: Operating System :: OS Independent
Requires-Dist: numpy
